git_repo/__init__.py
git_repo/exceptions.py
git_repo/extract_config.py
git_repo/kwargparse.py
git_repo/repo.py
git_repo/tools.py
git_repo/services/__init__.py
git_repo/services/service.py
git_repo/services/ext/__init__.py
git_repo/services/ext/bitbucket.py
git_repo/services/ext/gitbucket.py
git_repo/services/ext/github.py
git_repo/services/ext/gitlab.py
git_repo/services/ext/gogs.py
git_repo-1.10.3.dist-info/DESCRIPTION.rst
git_repo-1.10.3.dist-info/METADATA
git_repo-1.10.3.dist-info/RECORD
git_repo-1.10.3.dist-info/WHEEL
git_repo-1.10.3.dist-info/dependency_links.txt
git_repo-1.10.3.dist-info/entry_points.txt
git_repo-1.10.3.dist-info/metadata.json
git_repo-1.10.3.dist-info/top_level.txt
