Metadata-Version: 2.0
Name: git-repo
Version: 1.10.3
Summary: Tool for managing repository services from your git CLI tool
Home-page: https://github.com/guyzmo/git-repo
Author: Bernard `Guyzmo` Pratz
Author-email: guyzmo+git-repo@m0g.net
License: GPLv2
Keywords: git
Platform: UNKNOWN
Classifier: Development Status :: 4 - Beta
Classifier: Programming Language :: Python :: 3
Classifier: Programming Language :: Python :: 3.4
Classifier: Programming Language :: Python :: 3.5
Classifier: Environment :: Console
Classifier: Intended Audience :: Developers
Classifier: License :: OSI Approved :: GNU General Public License v2 (GPLv2)
Classifier: License :: OSI Approved :: GNU General Public License v3 (GPLv3)
Classifier: Topic :: Software Development
Classifier: Topic :: Software Development :: Version Control
Classifier: Topic :: Utilities
Requires-Dist: docopt
Requires-Dist: progress
Requires-Dist: python-dateutil
Requires-Dist: lxml
Requires-Dist: GitPython (>=2.1.0)
Requires-Dist: github3.py (<1.0.0)
Requires-Dist: python-gitlab (>=1.0.0)
Requires-Dist: gogs-client (>=1.0.3)
Requires-Dist: pybitbucket-fork (>=0.12.2)
